Metadata-Version: 2.1
Name: pcshell
Version: 0.2.3
Summary: Easily create robust Shell applications in Python with this extension for Click & Prompt-Toolkit; built with Windows OS in mind.
Home-page: https://github.com/xSlither/pretty-click-shell
Author: Chase M. Allen
License: UNKNOWN
Platform: UNKNOWN
Classifier: Development Status :: 3 - Alpha
Classifier: Environment :: Console
Classifier: Programming Language :: Python :: 3.8
Classifier: License :: OSI Approved :: MIT License
Classifier: Operating System :: OS Independent
Classifier: Intended Audience :: Developers
Classifier: Natural Language :: English
Classifier: Topic :: System :: Shells
Requires-Python: >=3.8
Requires-Dist: click (==7.1.2)
Requires-Dist: colorama
Requires-Dist: pygments
Requires-Dist: pyreadline
Requires-Dist: prompt-toolkit (==2.0.10)
